cena.py
setup.py
cena.egg-info/PKG-INFO
cena.egg-info/SOURCES.txt
cena.egg-info/dependency_links.txt
cena.egg-info/top_level.txt