Metadata-Version: 1.1
Name: cena
Version: 1.0.0
Summary: AND HIS NAME IS JOHN CENA
Home-page: https://github.com/rlucioni/cena
Author: Renzo Lucioni
Author-email: renzo@lucioni.email
License: MIT
Keywords: cena
Platform: UNKNOWN
Classifier: License :: OSI Approved :: MIT License
Classifier: Programming Language :: Python
Classifier: Topic :: Internet
